datalore/__init__.py
datalore/app.py
datalore/settings.py
datalore/domain/__init__.py
datalore/domain/bay.py
datalore/repository/__init__.py
datalore/repository/memrepo.py
datalore/rest/__init__.py
datalore/rest/bay.py
datalore/serializers/__init__.py
datalore/serializers/bay_serializer.py
datalore/shared/__init__.py
datalore/shared/domain_model.py
datalore/shared/request_object.py
datalore/shared/response_object.py
datalore/shared/use_case.py
datalore/use_cases/__init__.py
datalore/use_cases/bay_use_cases.py
datalore/use_cases/request_objects.py
datalore-0.1.0.dist-info/METADATA
datalore-0.1.0.dist-info/RECORD
datalore-0.1.0.dist-info/WHEEL
datalore-0.1.0.dist-info/top_level.txt
tests/domain/__init__.py
tests/domain/test_bay.py
tests/repository/__init__.py
tests/repository/test_memrepo.py
tests/serializers/__init__.py
tests/serializers/test_bay_serializer.py
tests/shared/__init__.py
tests/shared/test_request_object.py
tests/shared/test_response_object.py
tests/shared/test_use_case.py
tests/use_cases/__init__.py
tests/use_cases/test_bay_list_request_objects.py
tests/use_cases/test_bay_list_use_case.py
