Metadata-Version: 2.1
Name: datalore
Version: 0.1.0
Summary: Data Interface Abstraction Library
Home-page: https://github.com/RobotStudio/datalore
Author: Bobby Larson
Author-email: bobby@robot.studio
License: GNU General Public License v3
Keywords: database database-connection-wrapper datalore db data-interfacedata-sync data-synchronization
Platform: UNKNOWN
Classifier: Development Status :: 2 - Pre-Alpha
Classifier: Intended Audience :: Developers
Classifier: License :: OSI Approved :: GNU General Public License v3 (GPLv3)
Classifier: Natural Language :: English
Classifier: Programming Language :: Python :: 3.4
Classifier: Programming Language :: Python :: 3.5
Classifier: Programming Language :: Python :: 3.6
Requires-Dist: apiwrapper
